reynard_the_robot/__init__.py
reynard_the_robot/__main__.py
reynard_the_robot/ascii_socket.py
reynard_the_robot/gui.py
reynard_the_robot/main.py
reynard_the_robot/reynard.py
reynard_the_robot/robotraconteur.py
reynard_the_robot/web_static/app.js
reynard_the_robot/web_static/index.html
reynard_the_robot/web_static/reynard_arm_link.svg
reynard_the_robot/web_static/reynard_body.svg
reynard_the_robot/web_static/reynard_tool.svg
reynard_the_robot/web_static/rricon.ico
reynard_the_robot/web_static/rricon.png
reynard_the_robot/web_static/style.css
reynard_the_robot-0.2.2.dist-info/LICENSE.txt
reynard_the_robot-0.2.2.dist-info/METADATA
reynard_the_robot-0.2.2.dist-info/WHEEL
reynard_the_robot-0.2.2.dist-info/top_level.txt
reynard_the_robot-0.2.2.dist-info/RECORD
