Metadata-Version: 2.1
Name: reynard-the-robot
Version: 0.2.2
Summary: Reyndard the Robot Raconteur educational Robot
Author-email: John Wason <wason@wasontech.com>
License: Apache License
Project-URL: Documentation, https://github.com/robotraconteur/reynard-the-robot
Project-URL: Source, https://github.com/robotraconteur/reynard-the-robot
License-File: LICENSE.txt
Requires-Dist: robotraconteur
Requires-Dist: aiohttp
Requires-Dist: python-socketio
Requires-Dist: drekar-launch-process
Requires-Dist: importlib-resources
Requires-Dist: blinker
Requires-Dist: requests
Provides-Extra: gui
Requires-Dist: pyside6 ; extra == 'gui'
